setup.py
dsnd_prob_calc/Binomialdistribution.py
dsnd_prob_calc/Gaussiandistribution.py
dsnd_prob_calc/Generaldistribution.py
dsnd_prob_calc/__init__.py
dsnd_prob_calc.egg-info/PKG-INFO
dsnd_prob_calc.egg-info/SOURCES.txt
dsnd_prob_calc.egg-info/dependency_links.txt
dsnd_prob_calc.egg-info/not-zip-safe
dsnd_prob_calc.egg-info/top_level.txt