Metadata-Version: 1.0
Name: dsnd-prob-calc
Version: 0.1
Summary: Gaussian and Binomial distributions
Home-page: UNKNOWN
Author: David Usoro
Author-email: mulla.python@gmail.com
License: UNKNOWN
Platform: UNKNOWN
